{
  "experimentId": "exp_round_real_v2_20260206",
  "apiBase": "http://localhost:3010",
  "phrases": [
    "提示词工程",
    "API Gateway",
    "多模型对比"
  ],
  "rounds": [
    {
      "roundNumber": 0,
      "roundName": "baseline",
      "provider": "local",
      "variant": "baseline",
      "isTeacherReference": false,
      "fewshotOptions": {
        "enabled": false
      },
      "count": 3,
      "successCount": 3,
      "failCount": 0,
      "avgQuality": 78,
      "avgTokens": 1124.3333333333333,
      "avgLatency": 57610.333333333336
    },
    {
      "roundNumber": 1,
      "roundName": "fewshot_r1",
      "provider": "local",
      "variant": "fewshot_r1",
      "isTeacherReference": false,
      "fewshotOptions": {
        "enabled": true,
        "count": 1,
        "minScore": 80,
        "tokenBudgetRatio": 0.2
      },
      "count": 3,
      "successCount": 3,
      "failCount": 0,
      "avgQuality": 80,
      "avgTokens": 1166.6666666666667,
      "avgLatency": 62608.666666666664
    },
    {
      "roundNumber": 2,
      "roundName": "fewshot_r2",
      "provider": "local",
      "variant": "fewshot_r2",
      "isTeacherReference": false,
      "fewshotOptions": {
        "enabled": true,
        "count": 2,
        "minScore": 82,
        "tokenBudgetRatio": 0.22
      },
      "count": 3,
      "successCount": 3,
      "failCount": 0,
      "avgQuality": 78,
      "avgTokens": 1148,
      "avgLatency": 58626.666666666664
    },
    {
      "roundNumber": 3,
      "roundName": "fewshot_r3",
      "provider": "local",
      "variant": "fewshot_r3",
      "isTeacherReference": false,
      "fewshotOptions": {
        "enabled": true,
        "count": 3,
        "minScore": 85,
        "tokenBudgetRatio": 0.25
      },
      "count": 3,
      "successCount": 3,
      "failCount": 0,
      "avgQuality": 78,
      "avgTokens": 1134.6666666666667,
      "avgLatency": 56580.666666666664
    }
  ],
  "generatedAt": "2026-02-06T05:58:37.279Z"
}